ymdantic/__init__.py
ymdantic/mixins.py
ymdantic/py.typed
ymdantic/adapters/__init__.py
ymdantic/adapters/pydantic_factory.py
ymdantic/adapters/to_camel.py
ymdantic/client/__init__.py
ymdantic/client/yandex_music.py
ymdantic/client/session/__init__.py
ymdantic/client/session/aiohttp_client.py
ymdantic/client/session/aiohttp_method.py
ymdantic/enums/__init__.py
ymdantic/enums/editorial_artists.py
ymdantic/enums/editorial_compilation.py
ymdantic/enums/editorial_new_releases.py
ymdantic/enums/editorial_promotion.py
ymdantic/enums/language.py
ymdantic/enums/open_playlist.py
ymdantic/enums/special.py
ymdantic/exceptions/__init__.py
ymdantic/exceptions/custom_exceptions.py
ymdantic/models/__init__.py
ymdantic/models/action_button.py
ymdantic/models/base.py
ymdantic/models/chart_position.py
ymdantic/models/cover.py
ymdantic/models/custom_wave.py
ymdantic/models/error.py
ymdantic/models/pager.py
ymdantic/models/response.py
ymdantic/models/s3.py
ymdantic/models/theme.py
ymdantic/models/albums/__init__.py
ymdantic/models/albums/album.py
ymdantic/models/albums/label.py
ymdantic/models/artists/__init__.py
ymdantic/models/artists/artist.py
ymdantic/models/artists/artist_data.py
ymdantic/models/artists/artist_track_chart_position.py
ymdantic/models/artists/band_link_scanner_link.py
ymdantic/models/artists/concert.py
ymdantic/models/artists/counts.py
ymdantic/models/artists/description.py
ymdantic/models/artists/extra_action.py
ymdantic/models/artists/ratings.py
ymdantic/models/artists/social_link.py
ymdantic/models/artists/video.py
ymdantic/models/clips/__init__.py
ymdantic/models/clips/clip.py
ymdantic/models/concerts/__init__.py
ymdantic/models/concerts/city_case_forms.py
ymdantic/models/concerts/concert.py
ymdantic/models/landing/__init__.py
ymdantic/models/landing/album.py
ymdantic/models/landing/artist.py
ymdantic/models/landing/chart.py
ymdantic/models/landing/chart_block.py
ymdantic/models/landing/cover.py
ymdantic/models/landing/in_style.py
ymdantic-0.2.0.dist-info/METADATA
ymdantic-0.2.0.dist-info/WHEEL
ymdantic-0.2.0.dist-info/licenses/LICENSE
ymdantic-0.2.0.dist-info/RECORD
