Metadata-Version: 2.4
Name: ymdantic
Version: 0.2.0
Summary: Фреймворк предоставляющий доступ к API Яндекс Музыки (с Pydantic валидацией)
Author-email: KatantDev <vlad26@mail.ru>
License-File: LICENSE
Requires-Python: <3.14,>=3.10
Requires-Dist: aiohttp<4,>=3.9.0
Requires-Dist: certifi<2026,>=2025
Requires-Dist: dataclass-rest>=0.5.0
Requires-Dist: pydantic<3,>=2.4
Requires-Dist: strenum<0.5,>=0.4.15
